mexui/__init__.py
mexui/edit_command_ui.py
mexui/main_ui.py
mexui/settings_ui.py
mexui-1.0.2.dist-info/METADATA
mexui-1.0.2.dist-info/WHEEL
mexui-1.0.2.dist-info/top_level.txt
mexui-1.0.2.dist-info/RECORD
