Metadata-Version: 2.1
Name: mexui
Version: 1.0.2
Summary: Package with Mex Assistant's UI
Home-page: https://github.com/janinainfa/mex-assistant
Author: Janinainfa
Author-email: james@example.com
Classifier: Programming Language :: Python :: 3
Classifier: License :: OSI Approved :: MIT License
Classifier: Operating System :: OS Independent
Requires-Python: >=3.6
